[
  {
    "order": 0,
    "type": "organic",
    "html_handle": "rso[0]",
    "html_signature": "div.(no class)",
    "heading_text": "Zirh Shave Basics Kit - Amazon.com",
    "container": "rso",
    "container_index": "0"
  },
  {
    "order": 1,
    "type": "organic",
    "html_handle": "rso[1]",
    "html_signature": "div.g tF2Cxc",
    "heading_text": "Zirh Shave Basic Kit | Env\u00edo Gratuito | Lookfantastic",
    "container": "rso",
    "container_index": "1"
  },
  {
    "order": 2,
    "type": "organic",
    "html_handle": "rso[2]",
    "html_signature": "div.g",
    "heading_text": "Zirh Shave Basics Kit 679614310715 - eBay",
    "container": "rso",
    "container_index": "2"
  },
  {
    "order": 3,
    "type": "organic",
    "html_handle": "rso[3]",
    "html_signature": "div.hlcw0c",
    "heading_text": "Zirh Shave Basics Kit | Zirh Skin Care - MaleSkin Premium",
    "container": "rso",
    "container_index": "3"
  },
  {
    "order": 4,
    "type": "image_pack",
    "html_handle": "rso[4]",
    "html_signature": "h=\"imgs\" div.ULSxyf",
    "heading_text": "Images for buy zirh zirh shave basics kit",
    "container": "rso",
    "container_index": "4"
  },
  {
    "order": 5,
    "type": "organic",
    "html_handle": "rso[5]",
    "html_signature": "div.g tF2Cxc",
    "heading_text": "ZIRH Men's Skincare, Shave Basics Kit, PREPARE-SHAVE GEL ...",
    "container": "rso",
    "container_index": "5"
  },
  {
    "order": 6,
    "type": "knowledge_panel",
    "html_handle": "rso[6]",
    "html_signature": "h=\"comp\" div.TQc1id hSOk2e rhstc4",
    "heading_text": "Complementary results",
    "container": "rso",
    "container_index": "6"
  },
  {
    "order": 7,
    "type": "organic",
    "html_handle": "rso[7]",
    "html_signature": "div.g tF2Cxc",
    "heading_text": "ZIRH Shave Basics Kit Reviews 2022 - Influenster",
    "container": "rso",
    "container_index": "7"
  },
  {
    "order": 8,
    "type": "organic",
    "html_handle": "rso[8]",
    "html_signature": "div.g tF2Cxc",
    "heading_text": "Zirh Shave Basics Kit - Walmart.com",
    "container": "rso",
    "container_index": "8"
  },
  {
    "order": 9,
    "type": "organic",
    "html_handle": "rso[9]",
    "html_signature": "div.hlcw0c",
    "heading_text": "Zirh Shave Basics Kit | Buy Online | Mankind",
    "container": "rso",
    "container_index": "9"
  },
  {
    "order": 10,
    "type": "pagination",
    "html_handle": "botstuff.nav[0]",
    "html_signature": "div[role=navigation] in botstuff",
    "heading_text": "Page navigation|1|2|3|4|5|6|Next",
    "container": "botstuff",
    "container_index": 0
  }
]