[
  {
    "order": 0,
    "type": "organic",
    "html_handle": "rso[0]",
    "html_signature": "div.g tF2Cxc",
    "heading_text": "Meyle 1009190017 Temp Sensor : Automotive - Amazon.com",
    "container": "rso",
    "container_index": "0"
  },
  {
    "order": 1,
    "type": "organic",
    "html_handle": "rso[1]",
    "html_signature": "div.g tF2Cxc",
    "heading_text": "100 919 0017 MEYLE Sensor, coolant temperature ...",
    "container": "rso",
    "container_index": "1"
  },
  {
    "order": 2,
    "type": "organic",
    "html_handle": "rso[2]",
    "html_signature": "div.g tF2Cxc",
    "heading_text": "MEYLE 100 919 0017 Sensor, temperatura del ...",
    "container": "rso",
    "container_index": "2"
  },
  {
    "order": 3,
    "type": "knowledge_panel",
    "html_handle": "rso[3]",
    "html_signature": "h=\"comp\" div.TQc1id hSOk2e rhstc4",
    "heading_text": "Complementary results",
    "container": "rso",
    "container_index": "3"
  },
  {
    "order": 4,
    "type": "organic",
    "html_handle": "rso[4]",
    "html_signature": "div.(no class)",
    "heading_text": "Brand New Meyle Coolant Temperature Sensor ... - eBay",
    "container": "rso",
    "container_index": "4"
  },
  {
    "order": 5,
    "type": "organic",
    "html_handle": "rso[5]",
    "html_signature": "div.g",
    "heading_text": "MEYLE 100 919 0017 Sensor, coolant temperature ...",
    "container": "rso",
    "container_index": "5"
  },
  {
    "order": 6,
    "type": "organic",
    "html_handle": "rso[6]",
    "html_signature": "div.g tF2Cxc",
    "heading_text": "MEYLE Sensor, coolant temperature --, -40, 150\u00b0C, without ...",
    "container": "rso",
    "container_index": "6"
  },
  {
    "order": 7,
    "type": "organic",
    "html_handle": "rso[7]",
    "html_signature": "div.g tF2Cxc",
    "heading_text": "MEYLE Sensor, coolant temperature 100 919 0017 - spare parts",
    "container": "rso",
    "container_index": "7"
  },
  {
    "order": 8,
    "type": "organic",
    "html_handle": "rso[8]",
    "html_signature": "div.g tF2Cxc",
    "heading_text": "MEYLE 100 919 0017 Sensor, coolant temperature - Best Part ...",
    "container": "rso",
    "container_index": "8"
  },
  {
    "order": 9,
    "type": "organic",
    "html_handle": "rso[9]",
    "html_signature": "div.hlcw0c",
    "heading_text": "Sensor, temperatura del refrigerante MEYLE 1009190017 ...",
    "container": "rso",
    "container_index": "9"
  },
  {
    "order": 10,
    "type": "pagination",
    "html_handle": "botstuff.nav[0]",
    "html_signature": "div[role=navigation] in botstuff",
    "heading_text": "Page navigation|1|2|3|Next",
    "container": "botstuff",
    "container_index": 0
  }
]