[
  {
    "type": "organic",
    "x": 162.0,
    "y": 133.0,
    "width": 586.0,
    "height": 165.0,
    "html_handle": "rso[0]",
    "html_signature": "div.g",
    "heading_text": "Rozge Cosmeceutical - Renew Eyebrow Revitalizer Oil - ...",
    "source": "html_rso+cv_bbox",
    "position": 0
  },
  {
    "type": "organic",
    "x": 162.0,
    "y": 331.0,
    "width": 586.0,
    "height": 82.0,
    "html_handle": "rso[1]",
    "html_signature": "div.g tF2Cxc",
    "heading_text": "Rozge Cosmeceutical - Renew Eyebrow Revitalizer Oil",
    "source": "html_rso+cv_bbox",
    "position": 1
  },
  {
    "type": "organic",
    "x": 162.0,
    "y": 448.0,
    "width": 586.0,
    "height": 81.0,
    "html_handle": "rso[2]",
    "html_signature": "div.g tF2Cxc",
    "heading_text": "Rozge Cosmeceutical - Renew Eyebrow Revitalizer ... - Sears",
    "source": "html_rso+cv_bbox",
    "position": 2
  },
  {
    "type": "organic",
    "x": 162.0,
    "y": 564.0,
    "width": 586.0,
    "height": 183.0,
    "html_handle": "rso[3]",
    "html_signature": "div.(no class)",
    "heading_text": "Rozge Cosmeceutical-aceite Revitalizador De Cejas renovar",
    "source": "html_rso+cv_bbox",
    "position": 3
  },
  {
    "type": "organic",
    "x": 162.0,
    "y": 782.0,
    "width": 586.0,
    "height": 101.0,
    "html_handle": "rso[4]",
    "html_signature": "div.g tF2Cxc",
    "heading_text": "Rozge Renew Eyebrow Oil, 10ml/0.33 fl oz - eSkinStore",
    "source": "html_rso+cv_bbox",
    "position": 4
  },
  {
    "type": "organic",
    "x": 162.0,
    "y": 918.0,
    "width": 586.0,
    "height": 81.0,
    "html_handle": "rso[5]",
    "html_signature": "div.g tF2Cxc",
    "heading_text": "Rozge Cosmeceutical - Renew Eyebrow Revitalizer Oil - 0.33 oz",
    "source": "html_rso+cv_bbox",
    "position": 5
  },
  {
    "type": "organic",
    "x": 162.0,
    "y": 1034.0,
    "width": 586.0,
    "height": 81.0,
    "html_handle": "rso[6]",
    "html_signature": "div.hlcw0c",
    "heading_text": "Rozge Cosmeceutical - Renew Eyebrow Revitalizer Oil - 0.33 oz",
    "source": "html_rso+cv_bbox",
    "position": 6
  },
  {
    "type": "image_pack",
    "x": 162.0,
    "y": 1159.0,
    "width": 586.0,
    "height": 245.0,
    "html_handle": "rso[7]",
    "html_signature": "h=\"imgs\" div.ULSxyf",
    "heading_text": "Images for buy rozge cosmeceutical renew eyebrow oil",
    "source": "html_rso+cv_bbox",
    "position": 7
  },
  {
    "type": "organic",
    "x": 162.0,
    "y": 1447.0,
    "width": 586.0,
    "height": 81.0,
    "html_handle": "rso[8]",
    "html_signature": "div.hlcw0c",
    "heading_text": "Rozge Cosmeceutical - Renew Eyebrow Revitalizer Oil - 0.33 oz ...",
    "source": "html_rso+cv_bbox",
    "position": 8
  },
  {
    "type": "native_ad",
    "x": 162.0,
    "y": 1560.0,
    "width": 540.0,
    "height": 108.0,
    "html_handle": null,
    "html_signature": "",
    "heading_text": "",
    "source": "ad_only",
    "position": 9
  },
  {
    "type": "native_ad",
    "x": 162.0,
    "y": 1695.0,
    "width": 540.0,
    "height": 108.0,
    "html_handle": null,
    "html_signature": "",
    "heading_text": "",
    "source": "ad_only",
    "position": 10
  },
  {
    "type": "native_ad",
    "x": 162.0,
    "y": 1830.0,
    "width": 540.0,
    "height": 149.0,
    "html_handle": null,
    "html_signature": "",
    "heading_text": "",
    "source": "ad_only",
    "position": 11
  },
  {
    "type": "dd_right",
    "x": 802.0,
    "y": 158.0,
    "width": 221.0,
    "height": 535.0,
    "html_handle": null,
    "html_signature": "",
    "heading_text": "",
    "source": "cv_ad_rhs",
    "position": -1
  }
]