[
  {
    "type": "dd_top",
    "x": 162.0,
    "y": 158.0,
    "width": 586.0,
    "height": 351.0,
    "html_handle": null,
    "html_signature": "",
    "heading_text": "",
    "source": "ad_only",
    "position": 0
  },
  {
    "type": "organic",
    "x": 162.0,
    "y": 529.0,
    "width": 586.0,
    "height": 101.0,
    "html_handle": "rso[0]",
    "html_signature": "div.g tF2Cxc",
    "heading_text": "Monroe 71818 Sensa-Trac Strut - Amazon.ca",
    "source": "html_rso+cv_bbox",
    "position": 1
  },
  {
    "type": "organic",
    "x": 162.0,
    "y": 665.0,
    "width": 586.0,
    "height": 121.0,
    "html_handle": "rso[1]",
    "html_signature": "div.g tF2Cxc",
    "heading_text": "Monroe 71618 Sensa-Trac Strut - Amazon.com",
    "source": "html_rso+cv_bbox",
    "position": 2
  },
  {
    "type": "organic",
    "x": 162.0,
    "y": 821.0,
    "width": 586.0,
    "height": 101.0,
    "html_handle": "rso[2]",
    "html_signature": "div.g tF2Cxc",
    "heading_text": "Monroe 71818 - Monroe OESpectrum Strut | AutoAnything\u2122",
    "source": "html_rso+cv_bbox",
    "position": 3
  },
  {
    "type": "organic",
    "x": 162.0,
    "y": 956.0,
    "width": 586.0,
    "height": 81.0,
    "html_handle": "rso[3]",
    "html_signature": "div.g tF2Cxc",
    "heading_text": "71818 by MONROE - OESPECTRUM PREMIUM STRUT",
    "source": "html_rso+cv_bbox",
    "position": 4
  },
  {
    "type": "organic",
    "x": 162.0,
    "y": 1072.0,
    "width": 586.0,
    "height": 203.0,
    "html_handle": "rso[4]",
    "html_signature": "div.(no class)",
    "heading_text": "Monroe | Performance Shocks & Struts",
    "source": "html_rso+cv_bbox",
    "position": 5
  },
  {
    "type": "organic",
    "x": 162.0,
    "y": 1310.0,
    "width": 586.0,
    "height": 101.0,
    "html_handle": "rso[5]",
    "html_signature": "div.g tF2Cxc",
    "heading_text": "Monroe Sensa-Trac Strut | 9613591 - Pep Boys",
    "source": "html_rso+cv_bbox",
    "position": 6
  },
  {
    "type": "organic",
    "x": 162.0,
    "y": 1446.0,
    "width": 586.0,
    "height": 183.0,
    "html_handle": "rso[6]",
    "html_signature": "div.hlcw0c",
    "heading_text": "Monroe Shocks & Struts 37118 Sensa-Trac Shock Absorber",
    "source": "html_rso+cv_bbox",
    "position": 7
  },
  {
    "type": "image_pack",
    "x": 162.0,
    "y": 1674.0,
    "width": 586.0,
    "height": 202.0,
    "html_handle": "rso[7]",
    "html_signature": "h=\"imgs\" div.ULSxyf",
    "heading_text": "Images for buy monroe monroe 71818 sensa trac strut",
    "source": "html_rso+cv_bbox",
    "position": 8
  },
  {
    "type": "native_ad",
    "x": 162.0,
    "y": 1917.0,
    "width": 540.0,
    "height": 149.0,
    "html_handle": null,
    "html_signature": "",
    "heading_text": "",
    "source": "ad_only",
    "position": 9
  },
  {
    "type": "native_ad",
    "x": 162.0,
    "y": 2093.0,
    "width": 540.0,
    "height": 169.0,
    "html_handle": null,
    "html_signature": "",
    "heading_text": "",
    "source": "ad_only",
    "position": 10
  },
  {
    "type": "native_ad",
    "x": 162.0,
    "y": 2288.0,
    "width": 540.0,
    "height": 149.0,
    "html_handle": null,
    "html_signature": "",
    "heading_text": "",
    "source": "ad_only",
    "position": 11
  },
  {
    "type": "chrome",
    "x": 162.0,
    "y": 2479.0,
    "width": 586.0,
    "height": 76.0,
    "html_handle": null,
    "html_signature": "",
    "heading_text": "",
    "source": "cv_bbox_only+chrome_heuristic",
    "position": -1
  }
]