[
  {
    "type": "organic",
    "x": 162.0,
    "y": 234.0,
    "width": 586.0,
    "height": 101.0,
    "html_handle": "rso[0]",
    "html_signature": "div.g tF2Cxc",
    "heading_text": "Daphne's Headcovers \u2013 The Original Golf Animal Headcover",
    "source": "html_rso+cv_bbox",
    "position": 0
  },
  {
    "type": "organic",
    "x": 162.0,
    "y": 366.0,
    "width": 586.0,
    "height": 105.0,
    "html_handle": "rso[1]",
    "html_signature": "div.g tF2Cxc",
    "heading_text": "Amazon.com : Daphne's Horse Headcovers, Brown-White",
    "source": "html_rso+cv_bbox",
    "position": 1
  },
  {
    "type": "organic",
    "x": 162.0,
    "y": 502.0,
    "width": 586.0,
    "height": 105.0,
    "html_handle": "rso[2]",
    "html_signature": "div.g tF2Cxc",
    "heading_text": "Daphne's Headcovers Horse 460cc Driver Headcover - eBay",
    "source": "html_rso+cv_bbox",
    "position": 2
  },
  {
    "type": "organic",
    "x": 162.0,
    "y": 642.0,
    "width": 586.0,
    "height": 150.0,
    "html_handle": "rso[3]",
    "html_signature": "div.g tF2Cxc",
    "heading_text": "Daphne's Horse Headcovers, Golf Club Head Covers",
    "source": "html_rso+cv_bbox",
    "position": 3
  },
  {
    "type": "organic",
    "x": 162.0,
    "y": 826.0,
    "width": 586.0,
    "height": 81.0,
    "html_handle": "rso[4]",
    "html_signature": "div.g tF2Cxc",
    "heading_text": "Golf Wholesale - Brandfusion - Daphne's Headcovers - Horse",
    "source": "html_rso+cv_bbox",
    "position": 4
  },
  {
    "type": "organic",
    "x": 162.0,
    "y": 942.0,
    "width": 586.0,
    "height": 204.0,
    "html_handle": "rso[5]",
    "html_signature": "div.hlcw0c",
    "heading_text": "Daphne's Headcovers Horse Head Cover - DICK'S Sporting ...",
    "source": "html_rso+cv_bbox",
    "position": 5
  },
  {
    "type": "image_pack",
    "x": 162.0,
    "y": 1190.0,
    "width": 586.0,
    "height": 244.0,
    "html_handle": "rso[6]",
    "html_signature": "h=\"imgs\" div.ULSxyf",
    "heading_text": "Images for buy daphne's headcovers daphne's horse headcovers",
    "source": "html_rso+cv_bbox",
    "position": 6
  },
  {
    "type": "knowledge_panel",
    "x": 162.0,
    "y": 1478.0,
    "width": 586.0,
    "height": 81.0,
    "html_handle": "rso[7]",
    "html_signature": "h=\"comp\" div.TQc1id hSOk2e rhstc4",
    "heading_text": "Complementary results",
    "source": "html_rso+cv_bbox",
    "position": 7
  },
  {
    "type": "organic",
    "x": 162.0,
    "y": 1589.0,
    "width": 586.0,
    "height": 103.0,
    "html_handle": "rso[8]",
    "html_signature": "div.g tF2Cxc",
    "heading_text": "Daphne's Animal Headcovers - Horse - Morton Golf Sales",
    "source": "html_rso+cv_bbox",
    "position": 8
  },
  {
    "type": "native_ad",
    "x": 162.0,
    "y": 1726.0,
    "width": 540.0,
    "height": 108.0,
    "html_handle": null,
    "html_signature": "",
    "heading_text": "",
    "source": "ad_only",
    "position": 9
  },
  {
    "type": "native_ad",
    "x": 162.0,
    "y": 1861.0,
    "width": 540.0,
    "height": 69.0,
    "html_handle": null,
    "html_signature": "",
    "heading_text": "",
    "source": "ad_only",
    "position": 10
  },
  {
    "type": "native_ad",
    "x": 162.0,
    "y": 1957.0,
    "width": 540.0,
    "height": 108.0,
    "html_handle": null,
    "html_signature": "",
    "heading_text": "",
    "source": "ad_only",
    "position": 11
  },
  {
    "type": "organic",
    "x": 162.0,
    "y": 2298.0,
    "width": 586.0,
    "height": 102.0,
    "html_handle": "rso[9]",
    "html_signature": "div.hlcw0c",
    "heading_text": "Horse Golf Club Cover by Daphne's Headcovers",
    "source": "html_rso+cv_bbox",
    "position": 12
  },
  {
    "type": "related_searches",
    "x": null,
    "y": null,
    "width": null,
    "height": null,
    "html_handle": "botstuff.ULSxyf[0]",
    "html_signature": "h=\"rs\" div.ULSxyf",
    "heading_text": "Related searches",
    "source": "html_botstuff",
    "position": -1
  },
  {
    "type": "pagination",
    "x": null,
    "y": null,
    "width": null,
    "height": null,
    "html_handle": "botstuff.nav[0]",
    "html_signature": "div[role=navigation] in botstuff",
    "heading_text": "Page navigation|1|2|3|4|5|Next",
    "source": "html_botstuff",
    "position": -1
  },
  {
    "type": "dd_right",
    "x": 802.0,
    "y": 158.0,
    "width": 221.0,
    "height": 503.0,
    "html_handle": null,
    "html_signature": "",
    "heading_text": "",
    "source": "cv_ad_rhs",
    "position": -1
  },
  {
    "type": "chrome",
    "x": 162.0,
    "y": 2615.0,
    "width": 586.0,
    "height": 194.0,
    "html_handle": null,
    "html_signature": "",
    "heading_text": "",
    "source": "cv_bbox_only+chrome_heuristic",
    "position": -1
  }
]