[
  {
    "type": "native_ad",
    "x": 162.0,
    "y": 163.0,
    "width": 540.0,
    "height": 108.0,
    "html_handle": null,
    "html_signature": "",
    "heading_text": "",
    "source": "ad_only",
    "position": 0
  },
  {
    "type": "native_ad",
    "x": 162.0,
    "y": 298.0,
    "width": 540.0,
    "height": 89.0,
    "html_handle": null,
    "html_signature": "",
    "heading_text": "",
    "source": "ad_only",
    "position": 1
  },
  {
    "type": "native_ad",
    "x": 162.0,
    "y": 414.0,
    "width": 540.0,
    "height": 108.0,
    "html_handle": null,
    "html_signature": "",
    "heading_text": "",
    "source": "ad_only",
    "position": 2
  },
  {
    "type": "native_ad",
    "x": 162.0,
    "y": 549.0,
    "width": 540.0,
    "height": 108.0,
    "html_handle": null,
    "html_signature": "",
    "heading_text": "",
    "source": "ad_only",
    "position": 3
  },
  {
    "type": "organic",
    "x": 162.0,
    "y": 685.0,
    "width": 586.0,
    "height": 85.0,
    "html_handle": "rso[0]",
    "html_signature": "div.g tF2Cxc",
    "heading_text": "Peppermint Oil | d\u014dTERRA Essential Oils - doTERRA",
    "source": "html_rso+cv_bbox",
    "position": 4
  },
  {
    "type": "organic",
    "x": 162.0,
    "y": 801.0,
    "width": 586.0,
    "height": 227.0,
    "html_handle": "rso[1]",
    "html_signature": "div.(no class)",
    "heading_text": "doTERRA Peppermint Essential Oil - 15ml - Amazon.com",
    "source": "html_rso+cv_bbox",
    "position": 5
  },
  {
    "type": "knowledge_panel",
    "x": 162.0,
    "y": 1059.0,
    "width": 586.0,
    "height": 85.0,
    "html_handle": "rso[2]",
    "html_signature": "h=\"comp\" div.TQc1id hSOk2e rhstc4",
    "heading_text": "Complementary results",
    "source": "html_rso+cv_bbox",
    "position": 6
  },
  {
    "type": "organic",
    "x": 162.0,
    "y": 1175.0,
    "width": 586.0,
    "height": 102.0,
    "html_handle": "rso[3]",
    "html_signature": "div.g tF2Cxc",
    "heading_text": "d\u014dTERRA Peppermint Essential Oil - 15ml",
    "source": "html_rso+cv_bbox",
    "position": 7
  },
  {
    "type": "organic",
    "x": 162.0,
    "y": 1315.0,
    "width": 586.0,
    "height": 99.0,
    "html_handle": "rso[4]",
    "html_signature": "div.g tF2Cxc",
    "heading_text": "doTERRA Peppermint essential oil (15ml)",
    "source": "html_rso+cv_bbox",
    "position": 8
  },
  {
    "type": "organic",
    "x": 162.0,
    "y": 1450.0,
    "width": 586.0,
    "height": 127.0,
    "html_handle": "rso[5]",
    "html_signature": "div.g tF2Cxc",
    "heading_text": "d\u014dTERRA Peppermint Essential Oil - 15ml",
    "source": "html_rso+cv_bbox",
    "position": 9
  },
  {
    "type": "organic",
    "x": 162.0,
    "y": 1614.0,
    "width": 586.0,
    "height": 82.0,
    "html_handle": "rso[6]",
    "html_signature": "div.g",
    "heading_text": "doTERRA Peppermint Essential Oil - 15ml - Morocco",
    "source": "html_rso+cv_bbox",
    "position": 10
  },
  {
    "type": "organic",
    "x": 162.0,
    "y": 1730.0,
    "width": 586.0,
    "height": 82.0,
    "html_handle": "rso[7]",
    "html_signature": "div.g tF2Cxc",
    "heading_text": "doTERRA Peppermint Esssential Oil 15ml - Peter Louis",
    "source": "html_rso+cv_bbox",
    "position": 11
  },
  {
    "type": "organic",
    "x": 162.0,
    "y": 1847.0,
    "width": 586.0,
    "height": 99.0,
    "html_handle": "rso[8]",
    "html_signature": "div.g tF2Cxc",
    "heading_text": "doTERRA Peppermint Essential Oil 15ml",
    "source": "html_rso+cv_bbox",
    "position": 12
  },
  {
    "type": "native_ad",
    "x": 162.0,
    "y": 1978.0,
    "width": 540.0,
    "height": 89.0,
    "html_handle": null,
    "html_signature": "",
    "heading_text": "",
    "source": "ad_only",
    "position": 13
  },
  {
    "type": "organic",
    "x": 162.0,
    "y": 2388.0,
    "width": 586.0,
    "height": 194.0,
    "html_handle": "rso[9]",
    "html_signature": "div.hlcw0c",
    "heading_text": "DoTerra Peppermint Essential Oil 15ml - Replays Sports ...",
    "source": "html_rso+cv_bbox",
    "position": 14
  },
  {
    "type": "related_searches",
    "x": null,
    "y": null,
    "width": null,
    "height": null,
    "html_handle": "botstuff.ULSxyf[0]",
    "html_signature": "h=\"rs\" div.ULSxyf",
    "heading_text": "Related searches",
    "source": "html_botstuff",
    "position": -1
  },
  {
    "type": "pagination",
    "x": null,
    "y": null,
    "width": null,
    "height": null,
    "html_handle": "botstuff.nav[0]",
    "html_signature": "div[role=navigation] in botstuff",
    "heading_text": "Page navigation|1|2|3|4|5|6|7|Next",
    "source": "html_botstuff",
    "position": -1
  },
  {
    "type": "dd_right",
    "x": 802.0,
    "y": 158.0,
    "width": 221.0,
    "height": 1276.0,
    "html_handle": null,
    "html_signature": "",
    "heading_text": "",
    "source": "cv_ad_rhs",
    "position": -1
  }
]