[
  {
    "type": "native_ad",
    "x": 162.0,
    "y": 163.0,
    "width": 540.0,
    "height": 370.0,
    "html_handle": null,
    "html_signature": "",
    "heading_text": "",
    "source": "ad_only",
    "position": 0
  },
  {
    "type": "native_ad",
    "x": 162.0,
    "y": 560.0,
    "width": 540.0,
    "height": 109.0,
    "html_handle": null,
    "html_signature": "",
    "heading_text": "",
    "source": "ad_only",
    "position": 1
  },
  {
    "type": "organic",
    "x": 162.0,
    "y": 701.0,
    "width": 586.0,
    "height": 101.0,
    "html_handle": "rso[0]",
    "html_signature": "div.g tF2Cxc",
    "heading_text": "Motorcraft BRMC1 Brake Master Cylinder - Amazon",
    "source": "html_rso+cv_bbox",
    "position": 2
  },
  {
    "type": "organic",
    "x": 162.0,
    "y": 837.0,
    "width": 586.0,
    "height": 184.0,
    "html_handle": "rso[1]",
    "html_signature": "div.(no class)",
    "heading_text": "Brake Master Cylinder Motorcraft BRMC-1 for sale online | eBay",
    "source": "html_rso+cv_bbox",
    "position": 3
  },
  {
    "type": "organic",
    "x": 162.0,
    "y": 1051.0,
    "width": 586.0,
    "height": 85.0,
    "html_handle": "rso[2]",
    "html_signature": "div.g tF2Cxc",
    "heading_text": "Motorcraft\u00ae BRMC1 - Brake Master Cylinder - CARiD.com",
    "source": "html_rso+cv_bbox",
    "position": 4
  },
  {
    "type": "organic",
    "x": 162.0,
    "y": 1171.0,
    "width": 586.0,
    "height": 81.0,
    "html_handle": "rso[3]",
    "html_signature": "div.g tF2Cxc",
    "heading_text": "Motorcraft Brake Master Cylinder BRMC-1 - Walmart.com",
    "source": "html_rso+cv_bbox",
    "position": 5
  },
  {
    "type": "organic",
    "x": 162.0,
    "y": 1286.0,
    "width": 586.0,
    "height": 81.0,
    "html_handle": "rso[4]",
    "html_signature": "div.g tF2Cxc",
    "heading_text": "BRMC-1,MOTORCRAFT BRMC-1; Brake Master Cylinder",
    "source": "html_rso+cv_bbox",
    "position": 6
  },
  {
    "type": "organic",
    "x": 162.0,
    "y": 1402.0,
    "width": 586.0,
    "height": 81.0,
    "html_handle": "rso[5]",
    "html_signature": "div.g tF2Cxc",
    "heading_text": "Motorcraft BRMC1 Brake Master Cylinder - Sears",
    "source": "html_rso+cv_bbox",
    "position": 7
  },
  {
    "type": "organic",
    "x": 162.0,
    "y": 1518.0,
    "width": 586.0,
    "height": 81.0,
    "html_handle": "rso[6]",
    "html_signature": "div.hlcw0c",
    "heading_text": "Motorcraft Brake Master Cylinder BRMC-1 - The Home Depot",
    "source": "html_rso+cv_bbox",
    "position": 8
  },
  {
    "type": "image_pack",
    "x": 162.0,
    "y": 1644.0,
    "width": 586.0,
    "height": 244.0,
    "html_handle": "rso[7]",
    "html_signature": "h=\"imgs\" div.ULSxyf",
    "heading_text": "Images for buy motorcraft motorcraft brmc1 brake master cylinder",
    "source": "html_rso+cv_bbox",
    "position": 9
  },
  {
    "type": "organic",
    "x": 162.0,
    "y": 1932.0,
    "width": 586.0,
    "height": 81.0,
    "html_handle": "rso[8]",
    "html_signature": "div.hlcw0c",
    "heading_text": "MOTORCRAFT BRMC1 Master Cylinder | RockAuto",
    "source": "html_rso+cv_bbox",
    "position": 10
  },
  {
    "type": "native_ad",
    "x": 162.0,
    "y": 2044.0,
    "width": 540.0,
    "height": 108.0,
    "html_handle": null,
    "html_signature": "",
    "heading_text": "",
    "source": "ad_only",
    "position": 11
  },
  {
    "type": "native_ad",
    "x": 162.0,
    "y": 2179.0,
    "width": 540.0,
    "height": 169.0,
    "html_handle": null,
    "html_signature": "",
    "heading_text": "",
    "source": "ad_only",
    "position": 12
  },
  {
    "type": "native_ad",
    "x": 162.0,
    "y": 2375.0,
    "width": 540.0,
    "height": 169.0,
    "html_handle": null,
    "html_signature": "",
    "heading_text": "",
    "source": "ad_only",
    "position": 13
  },
  {
    "type": "pagination",
    "x": null,
    "y": null,
    "width": null,
    "height": null,
    "html_handle": "botstuff.nav[0]",
    "html_signature": "div[role=navigation] in botstuff",
    "heading_text": "Page navigation|1|2|3|4|Next",
    "source": "html_botstuff",
    "position": -1
  }
]