[
  {
    "x": 588.5,
    "y": 221
  },
  {
    "x": 381.9,
    "y": 362
  },
  {
    "x": 280.8,
    "y": 437.5
  },
  {
    "x": 247.4,
    "y": 436.4
  },
  {
    "x": 125.2,
    "y": 427.5
  },
  {
    "x": 117.5,
    "y": 435.3
  },
  {
    "x": 110.8,
    "y": 464.1
  },
  {
    "x": 129.7,
    "y": 449.7
  },
  {
    "x": 157.5,
    "y": 460.8
  },
  {
    "x": 130.8,
    "y": 387.5
  },
  {
    "x": 131.9,
    "y": 362
  },
  {
    "x": 403.9,
    "y": 56.6
  },
  {
    "x": 144.1,
    "y": 485.2
  },
  {
    "x": 108.6,
    "y": 421.9
  },
  {
    "x": 156.4,
    "y": 433
  },
  {
    "x": 278.6,
    "y": 491.9
  },
  {
    "x": 307.4,
    "y": 417.5
  },
  {
    "x": 417.4,
    "y": 415.3
  },
  {
    "x": 588.5,
    "y": 445.3
  },
  {
    "x": 405.2,
    "y": 480.8
  },
  {
    "x": 156.4,
    "y": 629.5
  },
  {
    "x": 181.9,
    "y": 553
  },
  {
    "x": 209.7,
    "y": 513
  },
  {
    "x": 446.3,
    "y": 569.6
  },
  {
    "x": 662.9,
    "y": 599.6
  },
  {
    "x": 184.1,
    "y": 580.7
  },
  {
    "x": 215.2,
    "y": 574.1
  },
  {
    "x": 240.8,
    "y": 537.4
  },
  {
    "x": 280.8,
    "y": 585.2
  },
  {
    "x": 378.5,
    "y": 576.3
  },
  {
    "x": 379.9,
    "y": 11.1
  },
  {
    "x": 249.7,
    "y": 940.5
  },
  {
    "x": 159.7,
    "y": 872.8
  },
  {
    "x": 185.2,
    "y": 840.5
  },
  {
    "x": 208.6,
    "y": 769.5
  },
  {
    "x": 279.7,
    "y": 548.5
  },
  {
    "x": 247.5,
    "y": 574.1
  },
  {
    "x": 208.6,
    "y": 582.9
  },
  {
    "x": 196.3,
    "y": 1195.9
  },
  {
    "x": 171.9,
    "y": 1172.6
  },
  {
    "x": 247.5,
    "y": 580.7
  },
  {
    "x": 330.8,
    "y": 569.6
  },
  {
    "x": 214.1,
    "y": 734
  },
  {
    "x": 206.3,
    "y": 715.1
  },
  {
    "x": 682.9,
    "y": 493
  },
  {
    "x": 848.8,
    "y": 466.3
  },
  {
    "x": 310.8,
    "y": 1185.9
  },
  {
    "x": 184.1,
    "y": 1191.4
  },
  {
    "x": 143,
    "y": 1158.1
  },
  {
    "x": 189.7,
    "y": 1330.2
  }
]