[
  {
    "type": "dd_top",
    "x": 162.0,
    "y": 158.0,
    "width": 587.0,
    "height": 351.0,
    "html_handle": null,
    "html_signature": "",
    "heading_text": "",
    "source": "ad_only",
    "position": 0
  },
  {
    "type": "organic",
    "x": 162.0,
    "y": 527.0,
    "width": 586.0,
    "height": 148.0,
    "html_handle": "rso[0]",
    "html_signature": "div.g",
    "heading_text": "Funko Jawa Bobble Head : Toys & Games - Amazon.com",
    "source": "html_rso+cv_bbox",
    "position": 1
  },
  {
    "type": "organic",
    "x": 162.0,
    "y": 677.0,
    "width": 586.0,
    "height": 137.0,
    "html_handle": "rso[1]",
    "html_signature": "div.g tF2Cxc",
    "heading_text": "Nuevo Funko Star Wars Bobble Head Jawa Pop | Compra Online a ...",
    "source": "html_rso+cv_bbox",
    "position": 2
  },
  {
    "type": "organic",
    "x": 162.0,
    "y": 816.0,
    "width": 586.0,
    "height": 132.0,
    "html_handle": "rso[2]",
    "html_signature": "div.g tF2Cxc",
    "heading_text": "Star Wars K-9 de Funko Jawa Pop. Vinilo Bobble Head",
    "source": "html_rso+cv_bbox",
    "position": 3
  },
  {
    "type": "organic",
    "x": 162.0,
    "y": 950.0,
    "width": 586.0,
    "height": 236.0,
    "html_handle": "rso[3]",
    "html_signature": "div.(no class)",
    "heading_text": "FUNKO Star Wars Jawa Bobble Head 2008 - eBay",
    "source": "html_rso+cv_bbox",
    "position": 4
  },
  {
    "type": "organic",
    "x": 162.0,
    "y": 1188.0,
    "width": 586.0,
    "height": 114.0,
    "html_handle": "rso[4]",
    "html_signature": "div.g tF2Cxc",
    "heading_text": "Funko Pop! Star Wars Jawa Bobble-Head Figure #20 -",
    "source": "html_rso+cv_bbox",
    "position": 5
  },
  {
    "type": "organic",
    "x": 162.0,
    "y": 1304.0,
    "width": 586.0,
    "height": 114.0,
    "html_handle": "rso[5]",
    "html_signature": "div.g tF2Cxc",
    "heading_text": "figura star wars jawa bobble-head funko en caja",
    "source": "html_rso+cv_bbox",
    "position": 6
  },
  {
    "type": "organic",
    "x": 162.0,
    "y": 1420.0,
    "width": 586.0,
    "height": 133.0,
    "html_handle": "rso[6]",
    "html_signature": "div.g tF2Cxc",
    "heading_text": "Funko POP! Star Wars Jawa Bobblehead (3.75 - Walmart",
    "source": "html_rso+cv_bbox",
    "position": 7
  },
  {
    "type": "organic",
    "x": 162.0,
    "y": 1555.0,
    "width": 586.0,
    "height": 140.0,
    "html_handle": "rso[7]",
    "html_signature": "div.hlcw0c",
    "heading_text": "Funko POP! Star Wars Jawa Vinyl Bobble Head #20 ...",
    "source": "html_rso+cv_bbox",
    "position": 8
  },
  {
    "type": "image_pack",
    "x": 162.0,
    "y": 1697.0,
    "width": 586.0,
    "height": 225.0,
    "html_handle": "rso[8]",
    "html_signature": "h=\"imgs\" div.ULSxyf",
    "heading_text": "Images for buy funko jawa bobble head",
    "source": "html_rso+cv_bbox",
    "position": 9
  },
  {
    "type": "native_ad",
    "x": 162.0,
    "y": 1962.0,
    "width": 540.0,
    "height": 108.0,
    "html_handle": null,
    "html_signature": "",
    "heading_text": "",
    "source": "ad_only",
    "position": 10
  },
  {
    "type": "native_ad",
    "x": 162.0,
    "y": 2097.0,
    "width": 540.0,
    "height": 129.0,
    "html_handle": null,
    "html_signature": "",
    "heading_text": "",
    "source": "ad_only",
    "position": 11
  },
  {
    "type": "native_ad",
    "x": 162.0,
    "y": 2253.0,
    "width": 540.0,
    "height": 108.0,
    "html_handle": null,
    "html_signature": "",
    "heading_text": "",
    "source": "ad_only",
    "position": 12
  },
  {
    "type": "pagination",
    "x": null,
    "y": null,
    "width": null,
    "height": null,
    "html_handle": "botstuff.nav[0]",
    "html_signature": "div[role=navigation] in botstuff",
    "heading_text": "Page navigation|1|2|3|4|5|6|Next",
    "source": "html_botstuff",
    "position": -1
  }
]