[
  {
    "type": "dd_top",
    "x": 162.0,
    "y": 158.0,
    "width": 586.0,
    "height": 296.0,
    "html_handle": null,
    "html_signature": "",
    "heading_text": "",
    "source": "ad_only",
    "position": 0
  },
  {
    "type": "native_ad",
    "x": 162.0,
    "y": 470.0,
    "width": 540.0,
    "height": 108.0,
    "html_handle": null,
    "html_signature": "",
    "heading_text": "",
    "source": "ad_only",
    "position": 1
  },
  {
    "type": "native_ad",
    "x": 162.0,
    "y": 605.0,
    "width": 540.0,
    "height": 69.0,
    "html_handle": null,
    "html_signature": "",
    "heading_text": "",
    "source": "ad_only",
    "position": 2
  },
  {
    "type": "image_pack",
    "x": 162.0,
    "y": 720.0,
    "width": 586.0,
    "height": 381.0,
    "html_handle": "rso[0]",
    "html_signature": "ULSxyf+img div.ULSxyf",
    "heading_text": "Find results on",
    "source": "html_rso+cv_bbox",
    "position": 3
  },
  {
    "type": "top_places",
    "x": 162.0,
    "y": 1103.0,
    "width": 586.0,
    "height": 123.0,
    "html_handle": "rso[1]",
    "html_signature": "h=\"local\" div.ULSxyf",
    "heading_text": "Local results",
    "source": "html_rso+cv_bbox",
    "position": 4
  },
  {
    "type": "organic",
    "x": 162.0,
    "y": 1228.0,
    "width": 586.0,
    "height": 175.0,
    "html_handle": "rso[2]",
    "html_signature": "div.g",
    "heading_text": "NARS Sheer Glow Foundation - Deauville (Light 4 - Amazon",
    "source": "html_rso+cv_bbox",
    "position": 5
  },
  {
    "type": "organic",
    "x": 162.0,
    "y": 1405.0,
    "width": 586.0,
    "height": 166.0,
    "html_handle": "rso[3]",
    "html_signature": "div.g tF2Cxc",
    "heading_text": "NARS Sheer Glow Foundation, Deauville/Light, 1 Ounce ...",
    "source": "html_rso+cv_bbox",
    "position": 6
  },
  {
    "type": "organic",
    "x": 162.0,
    "y": 1573.0,
    "width": 586.0,
    "height": 133.0,
    "html_handle": "rso[4]",
    "html_signature": "div.hlcw0c",
    "heading_text": "Sheer Glow Foundation Deauville | NARS Cosmetics",
    "source": "html_rso+cv_bbox",
    "position": 7
  },
  {
    "type": "paa",
    "x": 162.0,
    "y": 1708.0,
    "width": 586.0,
    "height": 142.0,
    "html_handle": "rso[5]",
    "html_signature": "h=\"paa\" div.ULSxyf",
    "heading_text": "People also ask",
    "source": "html_rso+cv_bbox",
    "position": 8
  },
  {
    "type": "organic",
    "x": 162.0,
    "y": 1852.0,
    "width": 586.0,
    "height": 169.0,
    "html_handle": "rso[6]",
    "html_signature": "div.(no class)",
    "heading_text": "NARS Sheer Glow Foundation 30ml Light 4 Deauville 6041",
    "source": "html_rso+cv_bbox",
    "position": 9
  },
  {
    "type": "organic",
    "x": 162.0,
    "y": 2023.0,
    "width": 586.0,
    "height": 312.0,
    "html_handle": "rso[7]",
    "html_signature": "div.g tF2Cxc",
    "heading_text": "Sheer Glow Foundation Deauville | NARS Cosmetics",
    "source": "html_rso+cv_bbox",
    "position": 10
  },
  {
    "type": "organic",
    "x": 162.0,
    "y": 2337.0,
    "width": 586.0,
    "height": 114.0,
    "html_handle": "rso[8]",
    "html_signature": "div.g tF2Cxc",
    "heading_text": "NARS Sheer Glow Foundation - Deauville (Light 4) 30ml/1oz",
    "source": "html_rso+cv_bbox",
    "position": 11
  },
  {
    "type": "organic",
    "x": 162.0,
    "y": 2453.0,
    "width": 586.0,
    "height": 114.0,
    "html_handle": "rso[9]",
    "html_signature": "div.hlcw0c",
    "heading_text": "Nars Sheer Glow Foundation Gobi desde 39,56 - Idealo",
    "source": "html_rso+cv_bbox",
    "position": 12
  },
  {
    "type": "image_pack",
    "x": 162.0,
    "y": 2569.0,
    "width": 586.0,
    "height": 186.0,
    "html_handle": "rso[10]",
    "html_signature": "h=\"imgs\" div.ULSxyf",
    "heading_text": "Images for buy nars nars sheer glow foundation deauville",
    "source": "html_rso+cv_bbox",
    "position": 13
  },
  {
    "type": "organic",
    "x": 162.0,
    "y": 2757.0,
    "width": 586.0,
    "height": 130.0,
    "html_handle": "rso[11]",
    "html_signature": "div.hlcw0c",
    "heading_text": "NARS Sheer Glow Foundation, Deauville, 1 Oz - Walmart.com",
    "source": "html_rso+cv_bbox",
    "position": 14
  },
  {
    "type": "native_ad",
    "x": 162.0,
    "y": 3179.0,
    "width": 540.0,
    "height": 149.0,
    "html_handle": null,
    "html_signature": "",
    "heading_text": "",
    "source": "ad_only",
    "position": 15
  },
  {
    "type": "native_ad",
    "x": 162.0,
    "y": 3356.0,
    "width": 540.0,
    "height": 128.0,
    "html_handle": null,
    "html_signature": "",
    "heading_text": "",
    "source": "ad_only",
    "position": 16
  },
  {
    "type": "native_ad",
    "x": 162.0,
    "y": 3510.0,
    "width": 540.0,
    "height": 129.0,
    "html_handle": null,
    "html_signature": "",
    "heading_text": "",
    "source": "ad_only",
    "position": 17
  },
  {
    "type": "related_searches",
    "x": null,
    "y": null,
    "width": null,
    "height": null,
    "html_handle": "botstuff.ULSxyf[0]",
    "html_signature": "h=\"rs\" div.ULSxyf",
    "heading_text": "Related searches",
    "source": "html_botstuff",
    "position": -1
  },
  {
    "type": "pagination",
    "x": null,
    "y": null,
    "width": null,
    "height": null,
    "html_handle": "botstuff.nav[0]",
    "html_signature": "div[role=navigation] in botstuff",
    "heading_text": "Page navigation|1|2|3|4|5|6|7|8|9|10|Next",
    "source": "html_botstuff",
    "position": -1
  },
  {
    "type": "chrome",
    "x": 162.0,
    "y": 2889.0,
    "width": 586.0,
    "height": 156.0,
    "html_handle": null,
    "html_signature": "",
    "heading_text": "",
    "source": "cv_bbox_only+chrome_heuristic",
    "position": -1
  },
  {
    "type": "chrome",
    "x": 162.0,
    "y": 3047.0,
    "width": 586.0,
    "height": 102.0,
    "html_handle": null,
    "html_signature": "",
    "heading_text": "",
    "source": "cv_bbox_only+chrome_heuristic",
    "position": -1
  },
  {
    "type": "chrome",
    "x": 162.0,
    "y": 3685.0,
    "width": 586.0,
    "height": 130.0,
    "html_handle": null,
    "html_signature": "",
    "heading_text": "",
    "source": "cv_bbox_only+chrome_heuristic",
    "position": -1
  }
]