[
  {
    "type": "dd_top",
    "x": 162.0,
    "y": 158.0,
    "width": 587.0,
    "height": 382.0,
    "html_handle": null,
    "html_signature": "",
    "heading_text": "",
    "source": "ad_only",
    "position": 0
  },
  {
    "type": "organic",
    "x": 162.0,
    "y": 559.0,
    "width": 586.0,
    "height": 135.0,
    "html_handle": "rso[0]",
    "html_signature": "div.g tF2Cxc",
    "heading_text": "Skywatch handheld windmeter Eole - Kiteworldshop.com",
    "source": "html_rso+cv_bbox",
    "position": 1
  },
  {
    "type": "organic",
    "x": 162.0,
    "y": 696.0,
    "width": 586.0,
    "height": 136.0,
    "html_handle": "rso[1]",
    "html_signature": "div.g tF2Cxc",
    "heading_text": "JDC Skywatch Eole Kite Windmeter by - Amazon.es",
    "source": "html_rso+cv_bbox",
    "position": 2
  },
  {
    "type": "organic",
    "x": 162.0,
    "y": 834.0,
    "width": 586.0,
    "height": 115.0,
    "html_handle": "rso[2]",
    "html_signature": "div.g tF2Cxc",
    "heading_text": "JDC Electronic Skywatch Eole Kite Windmeter - Amazon.com",
    "source": "html_rso+cv_bbox",
    "position": 3
  },
  {
    "type": "organic",
    "x": 162.0,
    "y": 951.0,
    "width": 586.0,
    "height": 114.0,
    "html_handle": "rso[3]",
    "html_signature": "div.g tF2Cxc",
    "heading_text": "Handheld anemometers - Skywatch Xplorer - Eole - Meteos",
    "source": "html_rso+cv_bbox",
    "position": 4
  },
  {
    "type": "organic",
    "x": 162.0,
    "y": 1067.0,
    "width": 586.0,
    "height": 132.0,
    "html_handle": "rso[4]",
    "html_signature": "div.g tF2Cxc",
    "heading_text": "Skywatch Eole Windmeter Anemometer: Wind Speed",
    "source": "html_rso+cv_bbox",
    "position": 5
  },
  {
    "type": "organic",
    "x": 162.0,
    "y": 1201.0,
    "width": 586.0,
    "height": 115.0,
    "html_handle": "rso[5]",
    "html_signature": "div.g tF2Cxc",
    "heading_text": "JDC Electronic Skywatch Eole Kite Windmeter - Gibraltar ...",
    "source": "html_rso+cv_bbox",
    "position": 6
  },
  {
    "type": "organic",
    "x": 162.0,
    "y": 1318.0,
    "width": 586.0,
    "height": 133.0,
    "html_handle": "rso[6]",
    "html_signature": "div.g tF2Cxc",
    "heading_text": "JDC Skywatch Eole Windmeter Weather Station - Fly2Base ...",
    "source": "html_rso+cv_bbox",
    "position": 7
  },
  {
    "type": "organic",
    "x": 162.0,
    "y": 1453.0,
    "width": 586.0,
    "height": 115.0,
    "html_handle": "rso[7]",
    "html_signature": "div.g tF2Cxc",
    "heading_text": "JDC Skywatch Digital Anemometer Eole-1 Windsurf / Kitesurf ...",
    "source": "html_rso+cv_bbox",
    "position": 8
  },
  {
    "type": "organic",
    "x": 162.0,
    "y": 1570.0,
    "width": 586.0,
    "height": 114.0,
    "html_handle": "rso[8]",
    "html_signature": "div.g tF2Cxc",
    "heading_text": "Skywatch handheld anemometer Eole 1 - Seashop",
    "source": "html_rso+cv_bbox",
    "position": 9
  },
  {
    "type": "organic",
    "x": 162.0,
    "y": 1686.0,
    "width": 586.0,
    "height": 97.0,
    "html_handle": "rso[9]",
    "html_signature": "div.hlcw0c",
    "heading_text": "Buy Skywatch wind meters online at Kitemana",
    "source": "html_rso+cv_bbox",
    "position": 10
  },
  {
    "type": "pagination",
    "x": null,
    "y": null,
    "width": null,
    "height": null,
    "html_handle": "botstuff.nav[0]",
    "html_signature": "div[role=navigation] in botstuff",
    "heading_text": "Page navigation|1|2|3|4|Next",
    "source": "html_botstuff",
    "position": -1
  }
]