[
  {
    "type": "dd_top",
    "x": 162.0,
    "y": 158.0,
    "width": 587.0,
    "height": 296.0,
    "html_handle": null,
    "html_signature": "",
    "heading_text": "",
    "source": "ad_only",
    "position": 0
  },
  {
    "type": "native_ad",
    "x": 162.0,
    "y": 469.0,
    "width": 540.0,
    "height": 149.0,
    "html_handle": null,
    "html_signature": "",
    "heading_text": "",
    "source": "ad_only",
    "position": 1
  },
  {
    "type": "organic",
    "x": 162.0,
    "y": 647.0,
    "width": 586.0,
    "height": 166.0,
    "html_handle": "rso[0]",
    "html_signature": "div.g",
    "heading_text": "Bluebonnet Nutrition, Chelated Iron, 18 mg, 90 Vegetable ...",
    "source": "html_rso+cv_bbox",
    "position": 2
  },
  {
    "type": "organic",
    "x": 162.0,
    "y": 815.0,
    "width": 586.0,
    "height": 276.0,
    "html_handle": "rso[1]",
    "html_signature": "div.(no class)",
    "heading_text": "BLUEBONNET Nutrition Albion\u00ae CHELATED Iron 18 mg",
    "source": "html_rso+cv_bbox",
    "position": 3
  },
  {
    "type": "organic",
    "x": 162.0,
    "y": 1093.0,
    "width": 586.0,
    "height": 134.0,
    "html_handle": "rso[2]",
    "html_signature": "div.g tF2Cxc",
    "heading_text": "Chelated Iron 18 mg - 90 Vegetable Capsules",
    "source": "html_rso+cv_bbox",
    "position": 4
  },
  {
    "type": "organic",
    "x": 162.0,
    "y": 1229.0,
    "width": 586.0,
    "height": 136.0,
    "html_handle": "rso[3]",
    "html_signature": "div.g tF2Cxc",
    "heading_text": "Bluebonnet Albion Chelated Iron 18 Mg, 90 Ct - Walmart",
    "source": "html_rso+cv_bbox",
    "position": 5
  },
  {
    "type": "organic",
    "x": 162.0,
    "y": 1367.0,
    "width": 586.0,
    "height": 113.0,
    "html_handle": "rso[4]",
    "html_signature": "div.g tF2Cxc",
    "heading_text": "Bluebonnet Nutrition Chelated Iron 18 mg 90 Vegetable ...",
    "source": "html_rso+cv_bbox",
    "position": 6
  },
  {
    "type": "organic",
    "x": 162.0,
    "y": 1482.0,
    "width": 586.0,
    "height": 134.0,
    "html_handle": "rso[5]",
    "html_signature": "div.g tF2Cxc",
    "heading_text": "Bluebonnet Nutrition, Chelated Iron, 18 ... - Health Central USA",
    "source": "html_rso+cv_bbox",
    "position": 7
  },
  {
    "type": "organic",
    "x": 162.0,
    "y": 1618.0,
    "width": 586.0,
    "height": 132.0,
    "html_handle": "rso[6]",
    "html_signature": "div.g tF2Cxc",
    "heading_text": "Bluebonnet Nutrition Albion\u00ae Chelated Iron -- 18 mg - Vitacost",
    "source": "html_rso+cv_bbox",
    "position": 8
  },
  {
    "type": "organic",
    "x": 162.0,
    "y": 1752.0,
    "width": 586.0,
    "height": 141.0,
    "html_handle": "rso[7]",
    "html_signature": "div.hlcw0c",
    "heading_text": "Kosher Albion Chelated Iron 18 mg (Gentle Ferrous ...",
    "source": "html_rso+cv_bbox",
    "position": 9
  },
  {
    "type": "image_pack",
    "x": 162.0,
    "y": 1895.0,
    "width": 586.0,
    "height": 265.0,
    "html_handle": "rso[8]",
    "html_signature": "h=\"imgs\" div.ULSxyf",
    "heading_text": "Images for buy blue bonnet iron 18mg 90 capsule",
    "source": "html_rso+cv_bbox",
    "position": 10
  },
  {
    "type": "native_ad",
    "x": 162.0,
    "y": 2201.0,
    "width": 540.0,
    "height": 89.0,
    "html_handle": null,
    "html_signature": "",
    "heading_text": "",
    "source": "ad_only",
    "position": 11
  },
  {
    "type": "native_ad",
    "x": 162.0,
    "y": 2316.0,
    "width": 540.0,
    "height": 69.0,
    "html_handle": null,
    "html_signature": "",
    "heading_text": "",
    "source": "ad_only",
    "position": 12
  },
  {
    "type": "pagination",
    "x": null,
    "y": null,
    "width": null,
    "height": null,
    "html_handle": "botstuff.nav[0]",
    "html_signature": "div[role=navigation] in botstuff",
    "heading_text": "Page navigation|1|2|3|4|5|6|7|8|Next",
    "source": "html_botstuff",
    "position": -1
  }
]